filtered_faiss_lookup_pkg/__init__.py
filtered_faiss_lookup_pkg/tools/__init__.py
filtered_faiss_lookup_pkg/tools/filtered_faiss_lookup_tool.py
filtered_faiss_lookup_pkg/tools/utils.py
filtered_faiss_lookup_pkg/yamls/filtered_faiss_lookup_tool.yaml
tests/__init__.py
filtered_faiss_lookup_pkg-0.0.1.dist-info/METADATA
filtered_faiss_lookup_pkg-0.0.1.dist-info/WHEEL
filtered_faiss_lookup_pkg-0.0.1.dist-info/entry_points.txt
filtered_faiss_lookup_pkg-0.0.1.dist-info/top_level.txt
filtered_faiss_lookup_pkg-0.0.1.dist-info/RECORD
